flytekitplugins_spark-1.16.11-py3.14-nspkg.pth
flytekitplugins/spark/__init__.py
flytekitplugins/spark/connector.py
flytekitplugins/spark/generic_task.py
flytekitplugins/spark/models.py
flytekitplugins/spark/pyspark_transformers.py
flytekitplugins/spark/schema.py
flytekitplugins/spark/sd_transformers.py
flytekitplugins/spark/task.py
flytekitplugins_spark-1.16.11.data/scripts/flytekit_install_spark3.sh
flytekitplugins_spark-1.16.11.dist-info/METADATA
flytekitplugins_spark-1.16.11.dist-info/WHEEL
flytekitplugins_spark-1.16.11.dist-info/entry_points.txt
flytekitplugins_spark-1.16.11.dist-info/namespace_packages.txt
flytekitplugins_spark-1.16.11.dist-info/top_level.txt
flytekitplugins_spark-1.16.11.dist-info/RECORD
